gwflow/__init__.py
gwflow/gwflow.py
gwflow-0.1.0a2.dist-info/licenses/LICENSE
gwflow-0.1.0a2.dist-info/METADATA
gwflow-0.1.0a2.dist-info/WHEEL
gwflow-0.1.0a2.dist-info/top_level.txt
gwflow-0.1.0a2.dist-info/RECORD
