Metadata-Version: 2.4
Name: gwflow
Version: 0.1.0a2
Summary: Normalizing flows for gravitational-wave analyses
Author-email: "Michael J. Williams" <michaeljw1@googlemail.com>
License: MIT
Project-URL: Homepage, https://github.com/mj-will/gwflow
Classifier: Programming Language :: Python :: 3
Requires-Python: >=3.10
License-File: LICENSE
Requires-Dist: zuko
Requires-Dist: torch
Provides-Extra: test
Requires-Dist: pytest; extra == "test"
Dynamic: license-file
